{
  "products": [
    {
      "id": "001",
      "name": "phone",
      "price": 1000
    },
    {
      "name": "Смартфон",
      "price": 20999,
      "id": "002"
    },
    {
      "id": "003",
      "name": "Пылесос",
      "price": 4690
    },
    {
      "id": "be5a",
      "name": "VacuumCleaner",
      "price": 300
    },
    {
      "id": "28e9",
      "name": "VacuumCleaner",
      "price": 300
    }
  ],
  "comments": [
    {
      "id": "1",
      "text": "a comment about post 1",
      "postId": "1"
    },
    {
      "id": "2",
      "text": "another comment about post 1",
      "postId": "1"
    }
  ],
  "profile": {
    "name": "user"
  }
}